README.md
setup.cfg
setup.py
onnxt5/__init__.py
onnxt5/api.py
onnxt5/huggingface_utilities.py
onnxt5/models.py
onnxt5.egg-info/PKG-INFO
onnxt5.egg-info/SOURCES.txt
onnxt5.egg-info/dependency_links.txt
onnxt5.egg-info/requires.txt
onnxt5.egg-info/top_level.txt