Metadata-Version: 2.1
Name: onnxt5
Version: 0.1.3
Summary: Blazing fast summarization, translation, text-generation, Q&A and more using T5 in ONNX
Home-page: https://github.com/abelriboulot/onnxt5
Author: Abel Riboulot
Author-email: abel@kta.io
License: apache-2.0
Download-URL: https://github.com/abelriboulot/onnxt5/archive/0.0.3.tar.gz
Project-URL: Repo, https://github.com/abelriboulot/onnxt5
Keywords: T5,ONNX,onnxruntime,NLP,transformer,generate text,summarization,translation,q&a,machine learning,inference,fast inference
Platform: UNKNOWN
Classifier: Development Status :: 3 - Alpha
Classifier: Intended Audience :: Developers
Classifier: Topic :: Scientific/Engineering :: Artificial Intelligence
Classifier: License :: OSI Approved :: Apache Software License
Classifier: Programming Language :: Python :: 3
Classifier: Programming Language :: Python :: 3.5
Classifier: Programming Language :: Python :: 3.6
Classifier: Programming Language :: Python :: 3.7
Classifier: Programming Language :: Python :: 3.8
Requires-Python: >=3.5, <4
Provides-Extra: dev
Provides-Extra: test
